ohmyi3/commands/entrypoint.py
ohmyi3/commands/generate.py
ohmyi3/commands/info.py
ohmyi3/commands/init.py
ohmyi3/config/app.py
ohmyi3/config/package.py
ohmyi3/i3ctl.py
ohmyi3/package/bootstrap.py
ohmyi3/package/provider.py
ohmyi3/stubs/README.md
ohmyi3/stubs/config.d/00-header.conf
ohmyi3/stubs/config.d/05-system.conf
ohmyi3/stubs/config.d/10-autostart.conf
ohmyi3/stubs/config.d/15-borders.conf
ohmyi3/stubs/config.d/20-navigation.conf
ohmyi3/stubs/config.d/80-applications.conf
ohmyi3/stubs/config.d/85-windows.conf
ohmyi3/stubs/config.d/90-gaps.conf
ohmyi3/stubs/config.py
ohmyi3/stubs/plugins/alacritty/__init__.py
ohmyi3/stubs/plugins/alacritty/alacritty.py
ohmyi3/stubs/plugins/archey3/__init__.py
ohmyi3/stubs/plugins/archey3/archey3.py
ohmyi3/stubs/plugins/nitrogen/__init__.py
ohmyi3/stubs/plugins/nitrogen/nitrogen.py
ohmyi3/stubs/plugins/polybar/__init__.py
ohmyi3/stubs/plugins/polybar/polybar.py
ohmyi3/stubs/themes/amber/background.jpg
ohmyi3/stubs/themes/amber/theme.conf
ohmyi3/stubs/themes/archlinux/background.jpg
ohmyi3/stubs/themes/archlinux/theme.conf
ohmyi3/stubs/themes/i3status.conf
ohmyi3/stubs/themes/manjaro/background.jpg
ohmyi3/stubs/themes/manjaro/theme.conf
ohmyi3/stubs/themes/pink/background.jpg
ohmyi3/stubs/themes/pink/theme.conf
ohmyi3/util.py
ohmyi3-0.1.8.dist-info/METADATA
ohmyi3-0.1.8.dist-info/WHEEL
ohmyi3-0.1.8.dist-info/entry_points.txt
ohmyi3-0.1.8.dist-info/licenses/LICENSE
ohmyi3-0.1.8.dist-info/RECORD
