Metadata-Version: 2.4
Name: ohmyi3
Version: 0.1.8
Summary: Dynamic i3 Configuration Manager
License-Expression: MIT
License-File: LICENSE
Author: Matthew Reschke
Author-email: mail@mreschke.com
Requires-Python: >=3.10
Classifier: Environment :: Console
Classifier: License :: OSI Approved :: MIT License
Classifier: Operating System :: OS Independent
Classifier: Typing :: Typed
Requires-Dist: uvicore (==0.3.17)
Project-URL: Documentation, https://github.com/ohmyi3/ohmyi3
Project-URL: Homepage, https://github.com/ohmyi3/ohmyi3
Project-URL: Repository, https://github.com/ohmyi3/ohmyi3
